wfdb/__init__.py
wfdb/io/__init__.py
wfdb/io/_coreio.py
wfdb/io/_header.py
wfdb/io/_signal.py
wfdb/io/_url.py
wfdb/io/annotation.py
wfdb/io/convert/__init__.py
wfdb/io/convert/csv.py
wfdb/io/convert/edf.py
wfdb/io/convert/matlab.py
wfdb/io/convert/tff.py
wfdb/io/convert/wav.py
wfdb/io/datasource.py
wfdb/io/download.py
wfdb/io/header.py
wfdb/io/record.py
wfdb/io/util.py
wfdb/plot/__init__.py
wfdb/plot/plot.py
wfdb/processing/__init__.py
wfdb/processing/basic.py
wfdb/processing/evaluate.py
wfdb/processing/filter.py
wfdb/processing/hr.py
wfdb/processing/peaks.py
wfdb/processing/qrs.py
wfdb/version.py
wfdb-4.1.1.dist-info/LICENSE
wfdb-4.1.1.dist-info/METADATA
wfdb-4.1.1.dist-info/WHEEL
wfdb-4.1.1.dist-info/RECORD
