Metadata-Version: 2.1
Name: wfdb
Version: 4.1.1
Summary: The WFDB Python package: tools for reading, writing, and processing physiologic signals and annotations.
Home-page: https://github.com/MIT-LCP/wfdb-python/
License: MIT
Author: The Laboratory for Computational Physiology
Author-email: contact@physionet.org
Requires-Python: >=3.7
Classifier: License :: OSI Approved :: MIT License
Classifier: Programming Language :: Python :: 3
Classifier: Programming Language :: Python :: 3.7
Classifier: Programming Language :: Python :: 3.8
Classifier: Programming Language :: Python :: 3.9
Classifier: Programming Language :: Python :: 3.10
Classifier: Programming Language :: Python :: 3.11
Provides-Extra: dev
Requires-Dist: SoundFile (>=0.10.0)
Requires-Dist: Sphinx (>=4.5.0) ; extra == "dev"
Requires-Dist: black (>=22.3.0) ; extra == "dev"
Requires-Dist: matplotlib (>=3.2.2)
Requires-Dist: numpy (>=1.10.1)
Requires-Dist: pandas (>=1.3.0)
Requires-Dist: pylint (>=2.13.7) ; extra == "dev"
Requires-Dist: pytest (>=7.1.1) ; extra == "dev"
Requires-Dist: pytest-xdist (>=2.5.0) ; extra == "dev"
Requires-Dist: requests (>=2.8.1)
Requires-Dist: scipy (>=1.0.0)
Project-URL: Documentation, https://wfdb.readthedocs.io/
Project-URL: Repository, https://github.com/MIT-LCP/wfdb-python/
